{
  "members":[
    {
      "name":"area_mask",
      "type":"int"
    },
    {
      "name":"attenuation",
      "type":"float"
    },
    {
      "name":"autoplay",
      "type":"bool"
    },
    {
      "name":"bus",
      "type":"String"
    },
    {
      "name":"max_distance",
      "type":"float"
    },
    {
      "name":"playing",
      "type":"bool"
    },
    {
      "name":"stream",
      "type":"AudioStream"
    },
    {
      "name":"volume_db",
      "type":"float"
    }
  ],
  "constants":[],
  "methods":[
    {
      "returns":"float",
      "name":"get_playback_position"
    },
    {
      "returns":"void",
      "name":"play",
      "args":[
        {
          "name":"from_position",
          "type":"float",
          "default":"0.0"
        }
      ]
    },
    {
      "returns":"void",
      "name":"seek",
      "args":[
        {
          "name":"to_position",
          "type":"float"
        }
      ]
    },
    {
      "returns":"void",
      "name":"stop"
    }
  ],
  "name":"AudioStreamPlayer2D",
  "inherits":"Node2D"
}